<?xml version="1.0" encoding="utf-8"?>
<labels>
	<label index="sq_AL">Албански (Албанија)</label>
	<label index="ar_DZ">Арапски (Алгерија)</label>
	<label index="ar_BH">Арапски (Бахрајн)</label>
	<label index="ar_EG">Арапски (Египат)</label>
	<label index="ar_IQ">Арапски (Ирак)</label>
	<label index="ar_JO">Арапски (Јордан)</label>
	<label index="ar_KW">Арапски (Куваит)</label>
	<label index="ar_LB">Арапски (Лебанија)</label>
	<label index="ar_LY">Арапски (Либија)</label>
	<label index="ar_MA">Арапски (Мароко)</label>
	<label index="ar_OM">Арапски (Оман)</label>
	<label index="ar_QA">Арапски (Катар)</label>
	<label index="ar_SA">Арапски (Сауди арабија)</label>
	<label index="ar_SD">Арапски (Судан)</label>
	<label index="ar_SY">Арапски (Сирија)</label>
	<label index="ar_TN">Арапски (Тунезија)</label>
	<label index="ar_AE">Арапски (Заједнички Арапски емирати</label>
	<label index="ar_YE">Арабски (Јемен)</label>
	<label index="be_BY">Белоруски (Беларусија)</label>
	<label index="bg_BG">Бугарски (Бугарска)</label>
	<label index="ca_ES">Каталански (Шпанија)</label>
	<label index="zh_CN">Кинески (Кина)</label>
	<label index="zh_HK">Кинески (Хонг Конг)</label>
	<label index="zh_SG">Кинески (Сингапур)</label>
	<label index="zh_TW">Кинески (Тајван)</label>
	<label index="hr_HR">Хрватски (Хрватска)</label>
	<label index="cs_CZ">Ћехски (Ћехија)</label>
	<label index="da_DK">Дански (Данска)</label>
	<label index="nl_BE">Холанђански (Белгија)</label>
	<label index="nl_NL">Холанђански (Холандија)</label>
	<label index="en_AU">Енглески (Аустралија)</label>
	<label index="en_CA">Енглески (Канадија)</label>
	<label index="en_IN">Енглески (Индија)</label>
	<label index="en_IE">Енглески (Ирска)</label>
	<label index="en_MT">Енглески (Малта)</label>
	<label index="en_NZ">Енглески (Нови Зеланд)</label>
	<label index="en_PH">Енглески (Филипини)</label>
	<label index="en_SG">Енглески (Сингапур)</label>
	<label index="en_ZA">Енглески (Јужна Африка)</label>
	<label index="en_GB">Енглески (Уједињено Краљевство)</label>
	<label index="en_US">Енглески (Сједињене Америчке Државе)</label>
	<label index="et_EE">Естонски (Естонија)</label>
	<label index="fi_FI">Фински (Финска)</label>
	<label index="fr_BE">Француски (Белгија)</label>
	<label index="fr_CA">Француски (Канада)</label>
	<label index="fr_FR">Француски (Француска)</label>
	<label index="fr_LU">Француски (Луксембург)</label>
	<label index="fr_CH">Француски (Швајцарска)</label>
	<label index="de_AT">Немачка (Аустрија)</label>
	<label index="de_DE">Немачка (Немачка)</label>
	<label index="de_LU">Немачка (Луксембург)</label>
	<label index="de_CH">Немачка (Швајцарска)</label>
	<label index="el_CY">Грчки (Кипар)</label>
	<label index="el_GR">Грчки (Грчка)</label>
	<label index="iw_IL">Хебрејски (Исраел)</label>
	<label index="hi_IN">Хинди (Индија)</label>
	<label index="hu_HU">Мађарски (Мађарска)</label>
	<label index="is_IS">Исландски (Исланд)</label>
	<label index="in_ID">Индонезија (Индонезијски)</label>
	<label index="ga_IE">Ирски (Ирска)</label>
	<label index="it_IT">Италијански (Италија)</label>
	<label index="it_CH">Италијански (Швајцарска)</label>
	<label index="ja_JP">Јапански (Јапан)</label>
	<label index="ko_KR">Кореански (Јужна Кореа)</label>
	<label index="lv_LV">Латвиски (Латванија)</label>
	<label index="lt_LT">Литвански (Литванија)</label>
	<label index="mk_MK">Македонски (Македонија)</label>
	<label index="ms_MY">Малајзијски (Малајзија)</label>
	<label index="mt_MT">Малтешки (Малта)</label>
	<label index="no_NO">Норвешки (Норвешка)</label>
	<label index="pl_PL">Пољски (Пољска)</label>
	<label index="pt_BR">Португалски (Бразилија)</label>
	<label index="pt_PT">Португалски (Португалија)</label>
	<label index="ro_RO">Румунски (Румунија)</label>
	<label index="ru_RU">Руски (Русија)</label>
	<label index="sr_BA">Српски (Босна и Херцеговина)</label>
	<label index="sr_ME">Српски (Црна Гора)</label>
	<label index="sr_CS">Српски (Србија и Црна Гора)</label>
	<label index="sr_RS">Српски (Србија)</label>
	<label index="sk_SK">Словачки (Словачка)</label>
	<label index="sl_SI">Словенски (Словенија)</label>
	<label index="es_AR">Шпански (Аргентина)</label>
	<label index="es_BO">Шпански (Боливија)</label>
	<label index="es_CL">Шпански (Чиле)</label>
	<label index="es_CO">Шпански (Колумбија)</label>
	<label index="es_CR">Шпански (Коста Рика)</label>
	<label index="es_DO">Шпански (Доминиканска Република)</label>
	<label index="es_EC">Шпански (Еквадор)</label>
	<label index="es_SV">Шпански (Ел Салвадор)</label>
	<label index="es_GT">Шпански (Гватемала)</label>
	<label index="es_HN">Шпански (Хондуре)</label>
	<label index="es_MX">Шпански (Мексико)</label>
	<label index="es_NI">Шпански (Никварагуа)</label>
	<label index="es_PA">Шпански (Панама)</label>
	<label index="es_PY">Шпански (Парагвај)</label>
	<label index="es_PE">Шпански (Перу)</label>
	<label index="es_PR">Шпански (Пуерто Рико)</label>
	<label index="es_ES">Шпански (Шпанија)</label>
	<label index="es_US">Шпански (Сједињене Америчке Државе)</label>
	<label index="es_UY">Шпански (Уругвај)</label>
	<label index="es_VE">Шпански (Венецуела)</label>
	<label index="sv_SE">Шведски (Шведска)</label>
	<label index="th_TH">Таи (Таиланд)</label>
	<label index="tr_TR">Турски (Турска)</label>
	<label index="uk_UA">Украјински (Украјина)</label>
	<label index="vi_VN">Вијетнамски (Вијетнам)</label>
</labels>
